[
  {
    "CITY": "Roanoke",
    "STATE_CODE": "VA",
    "HOMES_SOLD": 101,
    "MEDIAN_SALE_PRICE": 224000.0,
    "MEDIAN_SALE_PRICE_MOM": -0.1038207642,
    "MEDIAN_SALE_PRICE_YOY": -0.03448275862,
    "HOMES_SOLD_MOM": -0.3175675676,
    "HOMES_SOLD_YOY": 0.1098901099,
    "INVENTORY_MOM": 0.02140672783,
    "INVENTORY_YOY": 0.8659217877,
    "MEDIAN_DOM": 24.0,
    "MEDIAN_DOM_YOY": 7.0,
    "HEALTH_SCORE": 75,
    "ALERTS": [
      "Sales MoM: -31.8%",
      "Inventory YoY: 86.6%",
      "DOM YoY: 700.0%"
    ]
  },
  {
    "CITY": "Cave Spring",
    "STATE_CODE": "VA",
    "HOMES_SOLD": 28,
    "MEDIAN_SALE_PRICE": 367000.0,
    "MEDIAN_SALE_PRICE_MOM": -0.005420054201,
    "MEDIAN_SALE_PRICE_YOY": 0.0338028169,
    "HOMES_SOLD_MOM": -0.06666666667,
    "HOMES_SOLD_YOY": 0.2173913043,
    "INVENTORY_MOM": 0.3333333333,
    "INVENTORY_YOY": 0.5438596491,
    "MEDIAN_DOM": 18.0,
    "MEDIAN_DOM_YOY": -1.0,
    "HEALTH_SCORE": 78,
    "ALERTS": [
      "Inventory MoM: 33.3%",
      "Inventory YoY: 54.4%",
      "DOM YoY: -100.0%"
    ]
  },
  {
    "CITY": "Salem",
    "STATE_CODE": "VA",
    "HOMES_SOLD": 26,
    "MEDIAN_SALE_PRICE": 290000.0,
    "MEDIAN_SALE_PRICE_MOM": -0.04918032787,
    "MEDIAN_SALE_PRICE_YOY": -0.07936507937,
    "HOMES_SOLD_MOM": -0.2121212121,
    "HOMES_SOLD_YOY": 0.0,
    "INVENTORY_MOM": -0.06944444444,
    "INVENTORY_YOY": 0.3673469388,
    "MEDIAN_DOM": 21.0,
    "MEDIAN_DOM_YOY": 5.0,
    "HEALTH_SCORE": 83,
    "ALERTS": [
      "Sales MoM: -21.2%",
      "Inventory YoY: 36.7%",
      "DOM YoY: 500.0%"
    ]
  },
  {
    "CITY": "Hollins",
    "STATE_CODE": "VA",
    "HOMES_SOLD": 22,
    "MEDIAN_SALE_PRICE": 315000.0,
    "MEDIAN_SALE_PRICE_MOM": -0.02920101703,
    "MEDIAN_SALE_PRICE_YOY": 0.06703160277,
    "HOMES_SOLD_MOM": 0.2222222222,
    "HOMES_SOLD_YOY": 0.2222222222,
    "INVENTORY_MOM": -0.24,
    "INVENTORY_YOY": -0.02564102564,
    "MEDIAN_DOM": 31.0,
    "MEDIAN_DOM_YOY": 22.0,
    "HEALTH_SCORE": 93,
    "ALERTS": [
      "Sales MoM: 22.2%",
      "Inventory MoM: -24.0%",
      "DOM YoY: 2200.0%"
    ]
  },
  {
    "CITY": "North Shore",
    "STATE_CODE": "VA",
    "HOMES_SOLD": 21,
    "MEDIAN_SALE_PRICE": 625000.0,
    "MEDIAN_SALE_PRICE_MOM": -0.07062851535,
    "MEDIAN_SALE_PRICE_YOY": 0.213592233,
    "HOMES_SOLD_MOM": 1.625,
    "HOMES_SOLD_YOY": 1.333333333,
    "INVENTORY_MOM": -0.04444444444,
    "INVENTORY_YOY": 0.5357142857,
    "MEDIAN_DOM": 39.0,
    "MEDIAN_DOM_YOY": 12.0,
    "HEALTH_SCORE": 71,
    "ALERTS": [
      "Sales MoM: 162.5%",
      "Sales YoY: 133.3%",
      "Inventory YoY: 53.6%",
      "DOM YoY: 1200.0%"
    ]
  },
  {
    "CITY": "Rocky Mount",
    "STATE_CODE": "VA",
    "HOMES_SOLD": 7,
    "MEDIAN_SALE_PRICE": 218000.0,
    "MEDIAN_SALE_PRICE_MOM": -0.2456747405,
    "MEDIAN_SALE_PRICE_YOY": -0.03111111111,
    "HOMES_SOLD_MOM": 0.1666666667,
    "HOMES_SOLD_YOY": 6.0,
    "INVENTORY_MOM": -0.1666666667,
    "INVENTORY_YOY": 0.25,
    "MEDIAN_DOM": 7.0,
    "MEDIAN_DOM_YOY": -6.0,
    "HEALTH_SCORE": 85,
    "ALERTS": [
      "Price MoM: -24.6%",
      "Sales YoY: 600.0%",
      "DOM YoY: -600.0%"
    ]
  },
  {
    "CITY": "Vinton",
    "STATE_CODE": "VA",
    "HOMES_SOLD": 6,
    "MEDIAN_SALE_PRICE": 228750.0,
    "MEDIAN_SALE_PRICE_MOM": -0.06632653061,
    "MEDIAN_SALE_PRICE_YOY": -0.09226190476,
    "HOMES_SOLD_MOM": -0.3333333333,
    "HOMES_SOLD_YOY": -0.3333333333,
    "INVENTORY_MOM": -0.0625,
    "INVENTORY_YOY": -0.1666666667,
    "MEDIAN_DOM": 15.0,
    "MEDIAN_DOM_YOY": 9.0,
    "HEALTH_SCORE": 81,
    "ALERTS": [
      "Sales MoM: -33.3%",
      "Sales YoY: -33.3%",
      "DOM YoY: 900.0%"
    ]
  },
  {
    "CITY": "Westlake Corner",
    "STATE_CODE": "VA",
    "HOMES_SOLD": 6,
    "MEDIAN_SALE_PRICE": 994950.0,
    "MEDIAN_SALE_PRICE_MOM": -0.2287209302,
    "MEDIAN_SALE_PRICE_YOY": 0.4578021978,
    "HOMES_SOLD_MOM": 0.2,
    "HOMES_SOLD_YOY": 0.5,
    "INVENTORY_MOM": 0.3125,
    "INVENTORY_YOY": -0.16,
    "MEDIAN_DOM": 44.0,
    "MEDIAN_DOM_YOY": -16.0,
    "HEALTH_SCORE": 71,
    "ALERTS": [
      "Price MoM: -22.9%",
      "Price YoY: 45.8%",
      "Sales YoY: 50.0%",
      "Inventory MoM: 31.2%",
      "DOM YoY: -1600.0%"
    ]
  },
  {
    "CITY": "Union Hall",
    "STATE_CODE": "VA",
    "HOMES_SOLD": 5,
    "MEDIAN_SALE_PRICE": 1534999.0,
    "MEDIAN_SALE_PRICE_MOM": 3.70858589,
    "MEDIAN_SALE_PRICE_YOY": 0.6868120879,
    "HOMES_SOLD_MOM": 0.6666666667,
    "HOMES_SOLD_YOY": 0.0,
    "INVENTORY_MOM": -0.2307692308,
    "INVENTORY_YOY": -0.1666666667,
    "MEDIAN_DOM": 88.0,
    "MEDIAN_DOM_YOY": 69.0,
    "HEALTH_SCORE": 71,
    "ALERTS": [
      "Price MoM: 370.9%",
      "Price YoY: 68.7%",
      "Sales MoM: 66.7%",
      "Inventory MoM: -23.1%",
      "DOM YoY: 6900.0%"
    ]
  },
  {
    "CITY": "Cloverdale",
    "STATE_CODE": "VA",
    "HOMES_SOLD": 5,
    "MEDIAN_SALE_PRICE": 505000.0,
    "MEDIAN_SALE_PRICE_MOM": 0.1716937355,
    "MEDIAN_SALE_PRICE_YOY": 0.611333578,
    "HOMES_SOLD_MOM": 0.25,
    "HOMES_SOLD_YOY": 4.0,
    "INVENTORY_MOM": 0.0,
    "INVENTORY_YOY": 0.6666666667,
    "MEDIAN_DOM": 25.0,
    "MEDIAN_DOM_YOY": -38.0,
    "HEALTH_SCORE": 79,
    "ALERTS": [
      "Price YoY: 61.1%",
      "Sales MoM: 25.0%",
      "Sales YoY: 400.0%",
      "Inventory YoY: 66.7%",
      "DOM YoY: -3800.0%"
    ]
  },
  {
    "CITY": "Daleville",
    "STATE_CODE": "VA",
    "HOMES_SOLD": 4,
    "MEDIAN_SALE_PRICE": 397500.0,
    "MEDIAN_SALE_PRICE_MOM": -0.04790419162,
    "MEDIAN_SALE_PRICE_YOY": -0.205,
    "HOMES_SOLD_MOM": -0.3333333333,
    "HOMES_SOLD_YOY": -0.2,
    "INVENTORY_MOM": 0.1666666667,
    "INVENTORY_YOY": 2.5,
    "MEDIAN_DOM": 32.0,
    "MEDIAN_DOM_YOY": 17.0,
    "HEALTH_SCORE": 59,
    "ALERTS": [
      "Sales MoM: -33.3%",
      "Inventory YoY: 250.0%",
      "DOM YoY: 1700.0%"
    ]
  },
  {
    "CITY": "Blue Ridge",
    "STATE_CODE": "VA",
    "HOMES_SOLD": 4,
    "MEDIAN_SALE_PRICE": 377500.0,
    "MEDIAN_SALE_PRICE_MOM": -0.1656536634,
    "MEDIAN_SALE_PRICE_YOY": 0.1723602484,
    "HOMES_SOLD_MOM": 0.0,
    "HOMES_SOLD_YOY": 1.0,
    "INVENTORY_MOM": -0.25,
    "INVENTORY_YOY": 0.2,
    "MEDIAN_DOM": 49.0,
    "MEDIAN_DOM_YOY": 26.0,
    "HEALTH_SCORE": 83,
    "ALERTS": [
      "Sales YoY: 100.0%",
      "Inventory MoM: -25.0%",
      "DOM YoY: 2600.0%"
    ]
  },
  {
    "CITY": "Penhook",
    "STATE_CODE": "VA",
    "HOMES_SOLD": 3,
    "MEDIAN_SALE_PRICE": 935000.0,
    "MEDIAN_SALE_PRICE_MOM": -0.4776536313,
    "MEDIAN_SALE_PRICE_YOY": NaN,
    "HOMES_SOLD_MOM": -0.25,
    "HOMES_SOLD_YOY": NaN,
    "INVENTORY_MOM": 0.1818181818,
    "INVENTORY_YOY": NaN,
    "MEDIAN_DOM": 3.0,
    "MEDIAN_DOM_YOY": NaN,
    "HEALTH_SCORE": 72,
    "ALERTS": [
      "Price MoM: -47.8%",
      "Sales MoM: -25.0%"
    ]
  },
  {
    "CITY": "Laymantown",
    "STATE_CODE": "VA",
    "HOMES_SOLD": 2,
    "MEDIAN_SALE_PRICE": 357475.0,
    "MEDIAN_SALE_PRICE_MOM": -0.2056111111,
    "MEDIAN_SALE_PRICE_YOY": 0.03992727273,
    "HOMES_SOLD_MOM": -0.3333333333,
    "HOMES_SOLD_YOY": -0.5,
    "INVENTORY_MOM": 1.0,
    "INVENTORY_YOY": 1.0,
    "MEDIAN_DOM": 4.0,
    "MEDIAN_DOM_YOY": -25.0,
    "HEALTH_SCORE": 81,
    "ALERTS": [
      "Price MoM: -20.6%",
      "Sales MoM: -33.3%",
      "Sales YoY: -50.0%",
      "Inventory MoM: 100.0%",
      "Inventory YoY: 100.0%",
      "DOM YoY: -2500.0%"
    ]
  },
  {
    "CITY": "Ferrum",
    "STATE_CODE": "VA",
    "HOMES_SOLD": 1,
    "MEDIAN_SALE_PRICE": 285500.0,
    "MEDIAN_SALE_PRICE_MOM": 0.06397647699,
    "MEDIAN_SALE_PRICE_YOY": NaN,
    "HOMES_SOLD_MOM": -0.5,
    "HOMES_SOLD_YOY": NaN,
    "INVENTORY_MOM": NaN,
    "INVENTORY_YOY": NaN,
    "MEDIAN_DOM": 76.0,
    "MEDIAN_DOM_YOY": NaN,
    "HEALTH_SCORE": 62,
    "ALERTS": [
      "Sales MoM: -50.0%"
    ]
  },
  {
    "CITY": "Glenvar",
    "STATE_CODE": "VA",
    "HOMES_SOLD": 1,
    "MEDIAN_SALE_PRICE": 289000.0,
    "MEDIAN_SALE_PRICE_MOM": 0.1115384615,
    "MEDIAN_SALE_PRICE_YOY": NaN,
    "HOMES_SOLD_MOM": 0.0,
    "HOMES_SOLD_YOY": NaN,
    "INVENTORY_MOM": 1.0,
    "INVENTORY_YOY": NaN,
    "MEDIAN_DOM": 18.0,
    "MEDIAN_DOM_YOY": NaN,
    "HEALTH_SCORE": 80,
    "ALERTS": [
      "Inventory MoM: 100.0%"
    ]
  },
  {
    "CITY": "Henry Fork",
    "STATE_CODE": "VA",
    "HOMES_SOLD": 1,
    "MEDIAN_SALE_PRICE": 131000.0,
    "MEDIAN_SALE_PRICE_MOM": -0.01503759398,
    "MEDIAN_SALE_PRICE_YOY": NaN,
    "HOMES_SOLD_MOM": 0.0,
    "HOMES_SOLD_YOY": NaN,
    "INVENTORY_MOM": 1.0,
    "INVENTORY_YOY": NaN,
    "MEDIAN_DOM": 26.0,
    "MEDIAN_DOM_YOY": NaN,
    "HEALTH_SCORE": 72,
    "ALERTS": [
      "Inventory MoM: 100.0%"
    ]
  }
]